Metadata-Version: 2.1
Name: frapy
Version: 1.0.0
Summary: Client for frapy cloud
Home-page: https://frapy.net
Author: Aleksander Peczot
Author-email: peczot.a@gmail.com
License: apache-2.0
Download-URL: https://github.com/ap74062/frapy/archive/refs/tags/1.0.0.tar.gz
Keywords: CLOUD,COMPUTING,CLOUDCOMPUTING
Platform: UNKNOWN
Classifier: Development Status :: 3 - Alpha
Classifier: Intended Audience :: Developers
Classifier: Topic :: System :: Distributed Computing
Classifier: License :: OSI Approved :: Apache Software License
Classifier: Programming Language :: Python :: 3.7
Classifier: Programming Language :: Python :: 3.8
Classifier: Programming Language :: Python :: 3.9
Classifier: Programming Language :: Python :: 3.10
Classifier: Programming Language :: Python :: 3.11
